Archi & Syst/VHDL/mux.vhd
entity mux is
	port(A, B, C : IN BIT;
		 S : OUT BIT);
end mux;

architecture arch of mux is 
	begin
		S <= A when c = '0' else B;
end arch;

Archi & Syst/VHDL/simmux.vhd
entity testmux is 
end testmux;

architecture sim of testmux is 
	component mux
		port(A, B, C : IN BIT;
			 S : OUT BIT);
	end component;
	
	signal Ea, Eb, Ec, Q : BIT;

	begin 
		m : mux port map (Ea, Eb, Ec, Q);
		Ea <= '0', '1' after 50 ms, '0' after 150 ms;
		Eb <= '0', '1' after 70 ms, '0' after 100 ms, '1' after 170 ms, '0' after 190 ms;
		Ec <= '0', '1' after 120 ms;
end sim;

Archi & Syst/VHDL/testmux.vcd
$date
  Tue Mar  3 16:01:31 2020
$end
$version
  GHDL v0
$end
$timescale
  1 fs
$end
$scope module standard $end
$upscope $end
$scope module testmux $end
$var reg 1 ! ea $end
$var reg 1 " eb $end
$var reg 1 # ec $end
$var reg 1 $ q $end
$scope module m $end
$var reg 1 % a $end
$var reg 1 & b $end
$var reg 1 ' c $end
$var reg 1 ( s $end
$upscope $end
$upscope $end
$enddefinitions $end
#0
0!
0"
0#
0$
0%
0&
0'
0(
#50000000000000
1!
1$
1%
1(
#70000000000000
1"
1&
#100000000000000
0"
0&
#120000000000000
1#
0$
1'
0(
#150000000000000
0!
0%
#170000000000000
1"
1$
1&
1(
#190000000000000
0"
0$
0&
0(
